stdb_driver-0.3.2.dist-info/METADATA
stdb_driver-0.3.2.dist-info/WHEEL
stdb_driver-0.3.2.dist-info/licenses/LICENSE.txt
stdb_driver/__init__.py
stdb_driver/_stdb_driver_py.abi3.so
stdb_driver-0.3.2.dist-info/RECORD
