Metadata-Version: 2.4
Name: stdb-driver
Version: 0.3.2
Classifier: Development Status :: 4 - Beta
Classifier: Environment :: Console
Classifier: Intended Audience :: Developers
Classifier: Intended Audience :: Science/Research
Classifier: Intended Audience :: System Administrators
Classifier: License :: OSI Approved :: BSD License
Classifier: Operating System :: Microsoft :: Windows
Classifier: Operating System :: POSIX :: Linux
Classifier: Programming Language :: Python
Classifier: Programming Language :: Python :: 3
Classifier: Programming Language :: Python :: 3 :: Only
Classifier: Programming Language :: Python :: 3.10
Classifier: Programming Language :: Python :: 3.11
Classifier: Programming Language :: Python :: 3.12
Classifier: Programming Language :: Python :: 3.13
Classifier: Programming Language :: Python :: 3.14
Classifier: Programming Language :: Python :: Implementation :: CPython
Classifier: Programming Language :: Rust
Classifier: Topic :: Database
Classifier: Topic :: Database :: Database Engines/Servers
Classifier: Topic :: Scientific/Engineering
Classifier: Topic :: Scientific/Engineering :: GIS
Classifier: Topic :: Scientific/Engineering :: Information Analysis
Classifier: Topic :: Software Development
Requires-Dist: numpy~=2.0 ; extra == 'numpy'
Requires-Dist: pandas~=2.0 ; extra == 'pandas'
Requires-Dist: stdb-driver[numpy,pandas] ; extra == 'all'
Provides-Extra: numpy
Provides-Extra: pandas
Provides-Extra: all
License-File: LICENSE.txt
Summary: Mireo SpaceTime database connector
Keywords: mireo,spacetime,database,connector,table,schema,ingest,spatiotemporal
Author: Mireo
Maintainer-email: Zvonimir Jurelinac <zvonimir.jurelinac@mireo.com>
Requires-Python: >=3.10
